obsidian_to_typst/__init__.py
obsidian_to_typst/document.typ
obsidian_to_typst/obsidian_path.py
obsidian_to_typst/obsidian_to_typst.py
obsidian_to_typst/process_markdown.py
obsidian_to_typst-0.2.2.dist-info/METADATA
obsidian_to_typst-0.2.2.dist-info/WHEEL
obsidian_to_typst-0.2.2.dist-info/entry_points.txt
obsidian_to_typst-0.2.2.dist-info/RECORD
