Metadata-Version: 2.4
Name: obsidian-to-typst
Version: 0.2.2
Summary: Convert Obsidian vault documents to typst and pdfs
Project-URL: repository, https://github.com/drbartling/obsidian-to-typst
Author-email: Ryan Bartling <ryan.bartling@gmail.com>
License-Expression: MIT
Requires-Python: <3.14,>=3.11
Requires-Dist: click>=8.2.1
Requires-Dist: colorama>=0.4.6
Requires-Dist: colored-traceback>=0.3.0
Requires-Dist: coloredlogs>=15.0.1
Requires-Dist: pydantic>=2.7.1
